SeelmanQuantum/__init__.py
SeelmanQuantumLibrary-0.0.1.dist-info/LICENSE.md
SeelmanQuantumLibrary-0.0.1.dist-info/METADATA
SeelmanQuantumLibrary-0.0.1.dist-info/WHEEL
SeelmanQuantumLibrary-0.0.1.dist-info/top_level.txt
SeelmanQuantumLibrary-0.0.1.dist-info/RECORD
