Metadata-Version: 2.1
Name: SeelmanQuantumLibrary
Version: 0.0.1
Summary: A library of tools for quantum computing and simulation
Author: Peter Seelman
Author-email: <peter.seelman@jhuapl.edu>
License: UNKNOWN
Keywords: python,qiskit,haar random
Platform: UNKNOWN
Classifier: Development Status :: 3 - Alpha
Classifier: Intended Audience :: Education
Classifier: Programming Language :: Python :: 2
Classifier: Programming Language :: Python :: 3
Classifier: Operating System :: MacOS :: MacOS X
Classifier: Operating System :: Microsoft :: Windows
License-File: LICENSE.md
Requires-Dist: numpy
Requires-Dist: qiskit
Requires-Dist: pennylane
